tonygrad/__init__.py
tonygrad/engine.py
tonygrad/nn.py
tonygrad/trace_graph.py
tonygrad-2.0.0.dist-info/LICENSE
tonygrad-2.0.0.dist-info/METADATA
tonygrad-2.0.0.dist-info/WHEEL
tonygrad-2.0.0.dist-info/top_level.txt
tonygrad-2.0.0.dist-info/RECORD
